{
	"name": "001 Flujo Caja Inmobiliario",
	"properties": {
		"activities": [
			{
				"name": "Copy BD",
				"type": "Copy",
				"dependsOn": [],
				"policy": {
					"timeout": "0.12:00:00",
					"retry": 0,
					"retryIntervalInSeconds": 30,
					"secureOutput": false,
					"secureInput": false
				},
				"userProperties": [
					{
						"name": "Source",
						"value": "imsa-files/Modelo Flujo de Caja/Flujo Caja Proyectos Inmobiliarios/BD Histórica Flujos Caja.xlsx"
					},
					{
						"name": "Destination",
						"value": "imsa-files/@{'Modelo Flujo de Caja/Flujo Caja Proyectos Inmobiliarios'}/@{'BD Histórica Flujos de Caja.csv'}"
					}
				],
				"typeProperties": {
					"source": {
						"type": "ExcelSource",
						"storeSettings": {
							"type": "AzureBlobFSReadSettings",
							"recursive": true,
							"enablePartitionDiscovery": false
						}
					},
					"sink": {
						"type": "DelimitedTextSink",
						"storeSettings": {
							"type": "AzureBlobFSWriteSettings"
						},
						"formatSettings": {
							"type": "DelimitedTextWriteSettings",
							"quoteAllText": true,
							"fileExtension": ".txt"
						}
					},
					"enableStaging": false,
					"translator": {
						"type": "TabularTranslator",
						"mappings": [
							{
								"source": {
									"type": "String",
									"ordinal": 1
								},
								"sink": {
									"name": "RUT",
									"physicalType": "String"
								}
							},
							{
								"source": {
									"type": "String",
									"ordinal": 2
								},
								"sink": {
									"name": "Empresa",
									"physicalType": "String"
								}
							},
							{
								"source": {
									"type": "String",
									"ordinal": 3
								},
								"sink": {
									"name": "Proyecto",
									"physicalType": "String"
								}
							},
							{
								"source": {
									"type": "String",
									"ordinal": 4
								},
								"sink": {
									"name": "Segmento",
									"physicalType": "String"
								}
							},
							{
								"source": {
									"type": "String",
									"ordinal": 5
								},
								"sink": {
									"name": "Fecha",
									"physicalType": "String"
								}
							},
							{
								"source": {
									"type": "String",
									"ordinal": 6
								},
								"sink": {
									"name": "Importe",
									"physicalType": "String"
								}
							},
							{
								"source": {
									"type": "String",
									"ordinal": 7
								},
								"sink": {
									"name": "Importe_UF",
									"physicalType": "String"
								}
							},
							{
								"source": {
									"type": "String",
									"ordinal": 8
								},
								"sink": {
									"name": "ID_Proyecto",
									"physicalType": "String"
								}
							},
							{
								"source": {
									"type": "String",
									"ordinal": 9
								},
								"sink": {
									"name": "Etapa",
									"physicalType": "String"
								}
							},
							{
								"source": {
									"type": "String",
									"ordinal": 10
								},
								"sink": {
									"name": "NombreProyecto",
									"physicalType": "String"
								}
							},
							{
								"source": {
									"type": "String",
									"ordinal": 11
								},
								"sink": {
									"name": "Item_CC",
									"physicalType": "String"
								}
							},
							{
								"source": {
									"type": "String",
									"ordinal": 12
								},
								"sink": {
									"name": "Nombre_Item_CC",
									"physicalType": "String"
								}
							},
							{
								"source": {
									"type": "String",
									"ordinal": 13
								},
								"sink": {
									"name": "Texto_de_la_transacción",
									"physicalType": "String"
								}
							},
							{
								"source": {
									"type": "String",
									"ordinal": 14
								},
								"sink": {
									"name": "Descripcion_del_Diario",
									"physicalType": "String"
								}
							},
							{
								"source": {
									"type": "String",
									"ordinal": 15
								},
								"sink": {
									"name": "Mes",
									"physicalType": "String"
								}
							},
							{
								"source": {
									"type": "String",
									"ordinal": 16
								},
								"sink": {
									"name": "Año",
									"physicalType": "String"
								}
							}
						],
						"typeConversion": true,
						"typeConversionSettings": {
							"allowDataTruncation": true,
							"treatBooleanAsNumber": false
						}
					}
				},
				"inputs": [
					{
						"referenceName": "Excel_Flujo_Caja_Inmobiliario",
						"type": "DatasetReference"
					}
				],
				"outputs": [
					{
						"referenceName": "CSV_Datalake",
						"type": "DatasetReference",
						"parameters": {
							"Folder": "Modelo Flujo de Caja/Flujo Caja Proyectos Inmobiliarios",
							"File": "BD Histórica Flujos de Caja.csv"
						}
					}
				]
			}
		],
		"folder": {
			"name": "Flujo de Caja"
		},
		"annotations": []
	}
}